{
	"format_version": "1.8.0",
	"animations": {
		"animation.msdc0001.open": {
			"loop": "hold_on_last_frame",
			"animation_length": 3,
			"override_previous_animation": true,
			"bones": {
				"_DOORR_": {
					"position": {
						"0.0": [
							0,
							0,
							0
						],
						"2.0": [
							0,
							0,
							-15
						],
						"3.0": [
							0,
							0,
							-17
						]
					}
				},
				"_DOORL_": {
					"position": {
						"0.0": [
							0,
							0,
							0
						],
						"2.0": [
							0,
							0,
							15
						],
						"3.0": [
							0,
							0,
							17
						]
					}
				},
				"_LED_": {
					"position": [
						-1,
						0,
						0
					]
				},
				"off": {
					"position": {
						"0.0": [
							1,
							0,
							0
						],
						"3.0": [
							1,
							0,
							0
						]
					}
				}
			}
		},
		"animation.msdc0001.close": {
			"loop": "hold_on_last_frame",
			"animation_length": 2.5,
			"override_previous_animation": true,
			"bones": {
				"_DOORR_": {
					"position": {
						"0.0": [
							0,
							0,
							-17
						],
						"2.0": [
							0,
							0,
							-2
						],
						"2.5": [
							0,
							0,
							0
						]
					}
				},
				"_DOORL_": {
					"position": {
						"0.0": [
							0,
							0,
							17
						],
						"2.0": [
							0,
							0,
							2
						],
						"2.5": [
							0,
							0,
							0
						]
					}
				},
				"_LED_": {
					"position": {
						"0.0": [
							-1,
							0,
							0
						],
						"2.5": {
							"pre": [
								-1,
								0,
								0
							],
							"post": [
								0,
								0,
								0
							]
						}
					}
				},
				"off": {
					"position": {
						"0.0": [
							1,
							0,
							0
						],
						"2.5": {
							"pre": [
								1,
								0,
								0
							],
							"post": [
								0,
								0,
								0
							]
						}
					}
				}
			}
		},
		"animation.msdc0001.lcd_on": {
			"loop": true,
			"animation_length": 6,
			"bones": {
				"lcd_container": {
					"position": [
						0.1,
						0,
						0
					]
				},
				"lcd1": {
					"position": {
						"0.0": [
							-0.1,
							0,
							0
						],
						"3.0": {
							"pre": [
								-0.1,
								0,
								0
							],
							"post": [
								0,
								0,
								0
							]
						},
						"6.0": {
							"pre": [
								0,
								0,
								0
							],
							"post": [
								0,
								0,
								0
							]
						}
					}
				},
				"lcd2": {
					"position": {
						"0.0": [
							0,
							0,
							0
						],
						"3.0": {
							"pre": [
								0,
								0,
								0
							],
							"post": [
								-0.1,
								0,
								0
							]
						},
						"6.0": {
							"pre": [
								-0.1,
								0,
								0
							],
							"post": [
								0,
								0,
								0
							]
						}
					}
				}
			}
		},
		"animation.msdc0001.lcd_off": {
			"loop": "hold_on_last_frame",
			"bones": {
				"lcd_container": {
					"position": [
						0,
						0,
						0
					]
				},
				"lcd1": {
					"position": [
						0,
						0,
						0
					]
				},
				"lcd2": {
					"position": [
						0,
						0,
						0
					]
				}
			}
		},
		"animation.msdc0001.A1": {
			"loop": "hold_on_last_frame",
			"bones": {
				"A1": {
					"position": [
						-0.05,
						0,
						0
					]
				}
			}
		},
		"animation.msdc0001.A2": {
			"loop": "hold_on_last_frame",
			"bones": {
				"A2": {
					"position": [
						-0.05,
						0,
						0
					]
				}
			}
		},
		"animation.msdc0001.A3": {
			"loop": "hold_on_last_frame",
			"bones": {
				"A3": {
					"position": [
						-0.05,
						0,
						0
					]
				}
			}
		},
		"animation.msdc0001.A4": {
			"loop": "hold_on_last_frame",
			"bones": {
				"A4": {
					"position": [
						-0.05,
						0,
						0
					]
				}
			}
		},
		"animation.msdc0001.A5": {
			"loop": "hold_on_last_frame",
			"bones": {
				"A5": {
					"position": [
						-0.05,
						0,
						0
					]
				}
			}
		},
		"animation.msdc0001.A6": {
			"loop": "hold_on_last_frame",
			"bones": {
				"A6": {
					"position": [
						-0.05,
						0,
						0
					]
				}
			}
		},
		"animation.msdc0001.A7": {
			"loop": "hold_on_last_frame",
			"bones": {
				"A7": {
					"position": [
						-0.05,
						0,
						0
					]
				}
			}
		},
		"animation.msdc0001.A8": {
			"loop": "hold_on_last_frame",
			"bones": {
				"A8": {
					"position": [
						-0.05,
						0,
						0
					]
				}
			}
		},
		"animation.msdc0001.A9": {
			"loop": "hold_on_last_frame",
			"bones": {
				"A9": {
					"position": [
						-0.05,
						0,
						0
					]
				}
			}
		},
		"animation.msdc0001.A10": {
			"loop": "hold_on_last_frame",
			"bones": {
				"A10": {
					"position": [
						-0.05,
						0,
						0
					]
				}
			}
		},
		"animation.msdc0001.B1": {
			"loop": "hold_on_last_frame",
			"bones": {
				"B1": {
					"position": [
						-0.05,
						0,
						0
					]
				}
			}
		},
		"animation.msdc0001.B2": {
			"loop": "hold_on_last_frame",
			"bones": {
				"B2": {
					"position": [
						-0.05,
						0,
						0
					]
				}
			}
		},
		"animation.msdc0001.B3": {
			"loop": "hold_on_last_frame",
			"bones": {
				"B3": {
					"position": [
						-0.05,
						0,
						0
					]
				}
			}
		},
		"animation.msdc0001.B4": {
			"loop": "hold_on_last_frame",
			"bones": {
				"B4": {
					"position": [
						-0.05,
						0,
						0
					]
				}
			}
		},
		"animation.msdc0001.color1": {
			"loop": "hold_on_last_frame",
			"bones": {
				"c1": {
					"scale": [
						1,
						1,
						1
					]
				},
				"c2": {
					"scale": [
						0,
						0,
						0
					]
				},
				"c3": {
					"scale": [
						0,
						0,
						0
					]
				},
				"c4": {
					"scale": [
						0,
						0,
						0
					]
				},
				"c5": {
					"scale": [
						0,
						0,
						0
					]
				},
				"c6": {
					"scale": [
						0,
						0,
						0
					]
				},
				"c7": {
					"scale": [
						0,
						0,
						0
					]
				},
				"c8": {
					"scale": [
						0,
						0,
						0
					]
				},
				"c9": {
					"scale": [
						0,
						0,
						0
					]
				},
				"c10": {
					"scale": [
						0,
						0,
						0
					]
				},
				"c11": {
					"scale": [
						0,
						0,
						0
					]
				},
				"c12": {
					"scale": [
						0,
						0,
						0
					]
				},
				"c13": {
					"scale": [
						0,
						0,
						0
					]
				},
				"c14": {
					"scale": [
						0,
						0,
						0
					]
				},
				"c15": {
					"scale": [
						0,
						0,
						0
					]
				}
			}
		},
		"animation.msdc0001.color2": {
			"loop": "hold_on_last_frame",
			"bones": {
				"c1": {
					"scale": [
						0,
						0,
						0
					]
				},
				"c2": {
					"scale": [
						1,
						1,
						1
					]
				},
				"c3": {
					"scale": [
						0,
						0,
						0
					]
				},
				"c4": {
					"scale": [
						0,
						0,
						0
					]
				},
				"c5": {
					"scale": [
						0,
						0,
						0
					]
				},
				"c6": {
					"scale": [
						0,
						0,
						0
					]
				},
				"c7": {
					"scale": [
						0,
						0,
						0
					]
				},
				"c8": {
					"scale": [
						0,
						0,
						0
					]
				},
				"c9": {
					"scale": [
						0,
						0,
						0
					]
				},
				"c10": {
					"scale": [
						0,
						0,
						0
					]
				},
				"c11": {
					"scale": [
						0,
						0,
						0
					]
				},
				"c12": {
					"scale": [
						0,
						0,
						0
					]
				},
				"c13": {
					"scale": [
						0,
						0,
						0
					]
				},
				"c14": {
					"scale": [
						0,
						0,
						0
					]
				},
				"c15": {
					"scale": [
						0,
						0,
						0
					]
				}
			}
		},
		"animation.msdc0001.color3": {
			"loop": "hold_on_last_frame",
			"bones": {
				"c1": {
					"scale": [
						0,
						0,
						0
					]
				},
				"c2": {
					"scale": [
						0,
						0,
						0
					]
				},
				"c3": {
					"scale": [
						1,
						1,
						1
					]
				},
				"c4": {
					"scale": [
						0,
						0,
						0
					]
				},
				"c5": {
					"scale": [
						0,
						0,
						0
					]
				},
				"c6": {
					"scale": [
						0,
						0,
						0
					]
				},
				"c7": {
					"scale": [
						0,
						0,
						0
					]
				},
				"c8": {
					"scale": [
						0,
						0,
						0
					]
				},
				"c9": {
					"scale": [
						0,
						0,
						0
					]
				},
				"c10": {
					"scale": [
						0,
						0,
						0
					]
				},
				"c11": {
					"scale": [
						0,
						0,
						0
					]
				},
				"c12": {
					"scale": [
						0,
						0,
						0
					]
				},
				"c13": {
					"scale": [
						0,
						0,
						0
					]
				},
				"c14": {
					"scale": [
						0,
						0,
						0
					]
				},
				"c15": {
					"scale": [
						0,
						0,
						0
					]
				}
			}
		},
		"animation.msdc0001.color4": {
			"loop": "hold_on_last_frame",
			"bones": {
				"c1": {
					"scale": [
						0,
						0,
						0
					]
				},
				"c2": {
					"scale": [
						0,
						0,
						0
					]
				},
				"c3": {
					"scale": [
						0,
						0,
						0
					]
				},
				"c4": {
					"scale": [
						1,
						1,
						1
					]
				},
				"c5": {
					"scale": [
						0,
						0,
						0
					]
				},
				"c6": {
					"scale": [
						0,
						0,
						0
					]
				},
				"c7": {
					"scale": [
						0,
						0,
						0
					]
				},
				"c8": {
					"scale": [
						0,
						0,
						0
					]
				},
				"c9": {
					"scale": [
						0,
						0,
						0
					]
				},
				"c10": {
					"scale": [
						0,
						0,
						0
					]
				},
				"c11": {
					"scale": [
						0,
						0,
						0
					]
				},
				"c12": {
					"scale": [
						0,
						0,
						0
					]
				},
				"c13": {
					"scale": [
						0,
						0,
						0
					]
				},
				"c14": {
					"scale": [
						0,
						0,
						0
					]
				},
				"c15": {
					"scale": [
						0,
						0,
						0
					]
				}
			}
		},
		"animation.msdc0001.color5": {
			"loop": "hold_on_last_frame",
			"bones": {
				"c1": {
					"scale": [
						0,
						0,
						0
					]
				},
				"c2": {
					"scale": [
						0,
						0,
						0
					]
				},
				"c3": {
					"scale": [
						0,
						0,
						0
					]
				},
				"c4": {
					"scale": [
						0,
						0,
						0
					]
				},
				"c5": {
					"scale": [
						1,
						1,
						1
					]
				},
				"c6": {
					"scale": [
						0,
						0,
						0
					]
				},
				"c7": {
					"scale": [
						0,
						0,
						0
					]
				},
				"c8": {
					"scale": [
						0,
						0,
						0
					]
				},
				"c9": {
					"scale": [
						0,
						0,
						0
					]
				},
				"c10": {
					"scale": [
						0,
						0,
						0
					]
				},
				"c11": {
					"scale": [
						0,
						0,
						0
					]
				},
				"c12": {
					"scale": [
						0,
						0,
						0
					]
				},
				"c13": {
					"scale": [
						0,
						0,
						0
					]
				},
				"c14": {
					"scale": [
						0,
						0,
						0
					]
				},
				"c15": {
					"scale": [
						0,
						0,
						0
					]
				}
			}
		},
		"animation.msdc0001.color6": {
			"loop": "hold_on_last_frame",
			"bones": {
				"c1": {
					"scale": [
						0,
						0,
						0
					]
				},
				"c2": {
					"scale": [
						0,
						0,
						0
					]
				},
				"c3": {
					"scale": [
						0,
						0,
						0
					]
				},
				"c4": {
					"scale": [
						0,
						0,
						0
					]
				},
				"c5": {
					"scale": [
						0,
						0,
						0
					]
				},
				"c6": {
					"scale": [
						1,
						1,
						1
					]
				},
				"c7": {
					"scale": [
						0,
						0,
						0
					]
				},
				"c8": {
					"scale": [
						0,
						0,
						0
					]
				},
				"c9": {
					"scale": [
						0,
						0,
						0
					]
				},
				"c10": {
					"scale": [
						0,
						0,
						0
					]
				},
				"c11": {
					"scale": [
						0,
						0,
						0
					]
				},
				"c12": {
					"scale": [
						0,
						0,
						0
					]
				},
				"c13": {
					"scale": [
						0,
						0,
						0
					]
				},
				"c14": {
					"scale": [
						0,
						0,
						0
					]
				},
				"c15": {
					"scale": [
						0,
						0,
						0
					]
				}
			}
		},
		"animation.msdc0001.color7": {
			"loop": "hold_on_last_frame",
			"bones": {
				"c1": {
					"scale": [
						0,
						0,
						0
					]
				},
				"c2": {
					"scale": [
						0,
						0,
						0
					]
				},
				"c3": {
					"scale": [
						0,
						0,
						0
					]
				},
				"c4": {
					"scale": [
						0,
						0,
						0
					]
				},
				"c5": {
					"scale": [
						0,
						0,
						0
					]
				},
				"c6": {
					"scale": [
						0,
						0,
						0
					]
				},
				"c7": {
					"scale": [
						1,
						1,
						1
					]
				},
				"c8": {
					"scale": [
						0,
						0,
						0
					]
				},
				"c9": {
					"scale": [
						0,
						0,
						0
					]
				},
				"c10": {
					"scale": [
						0,
						0,
						0
					]
				},
				"c11": {
					"scale": [
						0,
						0,
						0
					]
				},
				"c12": {
					"scale": [
						0,
						0,
						0
					]
				},
				"c13": {
					"scale": [
						0,
						0,
						0
					]
				},
				"c14": {
					"scale": [
						0,
						0,
						0
					]
				},
				"c15": {
					"scale": [
						0,
						0,
						0
					]
				}
			}
		},
		"animation.msdc0001.color8": {
			"loop": "hold_on_last_frame",
			"bones": {
				"c1": {
					"scale": [
						0,
						0,
						0
					]
				},
				"c2": {
					"scale": [
						0,
						0,
						0
					]
				},
				"c3": {
					"scale": [
						0,
						0,
						0
					]
				},
				"c4": {
					"scale": [
						0,
						0,
						0
					]
				},
				"c5": {
					"scale": [
						0,
						0,
						0
					]
				},
				"c6": {
					"scale": [
						0,
						0,
						0
					]
				},
				"c7": {
					"scale": [
						0,
						0,
						0
					]
				},
				"c8": {
					"scale": [
						1,
						1,
						1
					]
				},
				"c9": {
					"scale": [
						0,
						0,
						0
					]
				},
				"c10": {
					"scale": [
						0,
						0,
						0
					]
				},
				"c11": {
					"scale": [
						0,
						0,
						0
					]
				},
				"c12": {
					"scale": [
						0,
						0,
						0
					]
				},
				"c13": {
					"scale": [
						0,
						0,
						0
					]
				},
				"c14": {
					"scale": [
						0,
						0,
						0
					]
				},
				"c15": {
					"scale": [
						0,
						0,
						0
					]
				}
			}
		},
		"animation.msdc0001.color9": {
			"loop": "hold_on_last_frame",
			"bones": {
				"c1": {
					"scale": [
						0,
						0,
						0
					]
				},
				"c2": {
					"scale": [
						0,
						0,
						0
					]
				},
				"c3": {
					"scale": [
						0,
						0,
						0
					]
				},
				"c4": {
					"scale": [
						0,
						0,
						0
					]
				},
				"c5": {
					"scale": [
						0,
						0,
						0
					]
				},
				"c6": {
					"scale": [
						0,
						0,
						0
					]
				},
				"c7": {
					"scale": [
						0,
						0,
						0
					]
				},
				"c8": {
					"scale": [
						0,
						0,
						0
					]
				},
				"c9": {
					"scale": [
						1,
						1,
						1
					]
				},
				"c10": {
					"scale": [
						0,
						0,
						0
					]
				},
				"c11": {
					"scale": [
						0,
						0,
						0
					]
				},
				"c12": {
					"scale": [
						0,
						0,
						0
					]
				},
				"c13": {
					"scale": [
						0,
						0,
						0
					]
				},
				"c14": {
					"scale": [
						0,
						0,
						0
					]
				},
				"c15": {
					"scale": [
						0,
						0,
						0
					]
				}
			}
		},
		"animation.msdc0001.color10": {
			"loop": "hold_on_last_frame",
			"bones": {
				"c1": {
					"scale": [
						0,
						0,
						0
					]
				},
				"c2": {
					"scale": [
						0,
						0,
						0
					]
				},
				"c3": {
					"scale": [
						0,
						0,
						0
					]
				},
				"c4": {
					"scale": [
						0,
						0,
						0
					]
				},
				"c5": {
					"scale": [
						0,
						0,
						0
					]
				},
				"c6": {
					"scale": [
						0,
						0,
						0
					]
				},
				"c7": {
					"scale": [
						0,
						0,
						0
					]
				},
				"c8": {
					"scale": [
						0,
						0,
						0
					]
				},
				"c9": {
					"scale": [
						0,
						0,
						0
					]
				},
				"c10": {
					"scale": [
						1,
						1,
						1
					]
				},
				"c11": {
					"scale": [
						0,
						0,
						0
					]
				},
				"c12": {
					"scale": [
						0,
						0,
						0
					]
				},
				"c13": {
					"scale": [
						0,
						0,
						0
					]
				},
				"c14": {
					"scale": [
						0,
						0,
						0
					]
				},
				"c15": {
					"scale": [
						0,
						0,
						0
					]
				}
			}
		},
		"animation.msdc0001.color11": {
			"loop": "hold_on_last_frame",
			"bones": {
				"c1": {
					"scale": [
						0,
						0,
						0
					]
				},
				"c2": {
					"scale": [
						0,
						0,
						0
					]
				},
				"c3": {
					"scale": [
						0,
						0,
						0
					]
				},
				"c4": {
					"scale": [
						0,
						0,
						0
					]
				},
				"c5": {
					"scale": [
						0,
						0,
						0
					]
				},
				"c6": {
					"scale": [
						0,
						0,
						0
					]
				},
				"c7": {
					"scale": [
						0,
						0,
						0
					]
				},
				"c8": {
					"scale": [
						0,
						0,
						0
					]
				},
				"c9": {
					"scale": [
						0,
						0,
						0
					]
				},
				"c10": {
					"scale": [
						0,
						0,
						0
					]
				},
				"c11": {
					"scale": [
						1,
						1,
						1
					]
				},
				"c12": {
					"scale": [
						0,
						0,
						0
					]
				},
				"c13": {
					"scale": [
						0,
						0,
						0
					]
				},
				"c14": {
					"scale": [
						0,
						0,
						0
					]
				},
				"c15": {
					"scale": [
						0,
						0,
						0
					]
				}
			}
		},
		"animation.msdc0001.color12": {
			"loop": "hold_on_last_frame",
			"bones": {
				"c1": {
					"scale": [
						0,
						0,
						0
					]
				},
				"c2": {
					"scale": [
						0,
						0,
						0
					]
				},
				"c3": {
					"scale": [
						0,
						0,
						0
					]
				},
				"c4": {
					"scale": [
						0,
						0,
						0
					]
				},
				"c5": {
					"scale": [
						0,
						0,
						0
					]
				},
				"c6": {
					"scale": [
						0,
						0,
						0
					]
				},
				"c7": {
					"scale": [
						0,
						0,
						0
					]
				},
				"c8": {
					"scale": [
						0,
						0,
						0
					]
				},
				"c9": {
					"scale": [
						0,
						0,
						0
					]
				},
				"c10": {
					"scale": [
						0,
						0,
						0
					]
				},
				"c11": {
					"scale": [
						0,
						0,
						0
					]
				},
				"c12": {
					"scale": [
						1,
						1,
						1
					]
				},
				"c13": {
					"scale": [
						0,
						0,
						0
					]
				},
				"c14": {
					"scale": [
						0,
						0,
						0
					]
				},
				"c15": {
					"scale": [
						0,
						0,
						0
					]
				}
			}
		},
		"animation.msdc0001.color13": {
			"loop": "hold_on_last_frame",
			"bones": {
				"c1": {
					"scale": [
						0,
						0,
						0
					]
				},
				"c2": {
					"scale": [
						0,
						0,
						0
					]
				},
				"c3": {
					"scale": [
						0,
						0,
						0
					]
				},
				"c4": {
					"scale": [
						0,
						0,
						0
					]
				},
				"c5": {
					"scale": [
						0,
						0,
						0
					]
				},
				"c6": {
					"scale": [
						0,
						0,
						0
					]
				},
				"c7": {
					"scale": [
						0,
						0,
						0
					]
				},
				"c8": {
					"scale": [
						0,
						0,
						0
					]
				},
				"c9": {
					"scale": [
						0,
						0,
						0
					]
				},
				"c10": {
					"scale": [
						0,
						0,
						0
					]
				},
				"c11": {
					"scale": [
						0,
						0,
						0
					]
				},
				"c12": {
					"scale": [
						0,
						0,
						0
					]
				},
				"c13": {
					"scale": [
						1,
						1,
						1
					]
				},
				"c14": {
					"scale": [
						0,
						0,
						0
					]
				},
				"c15": {
					"scale": [
						0,
						0,
						0
					]
				}
			}
		},
		"animation.msdc0001.color14": {
			"loop": "hold_on_last_frame",
			"bones": {
				"c1": {
					"scale": [
						0,
						0,
						0
					]
				},
				"c2": {
					"scale": [
						0,
						0,
						0
					]
				},
				"c3": {
					"scale": [
						0,
						0,
						0
					]
				},
				"c4": {
					"scale": [
						0,
						0,
						0
					]
				},
				"c5": {
					"scale": [
						0,
						0,
						0
					]
				},
				"c6": {
					"scale": [
						0,
						0,
						0
					]
				},
				"c7": {
					"scale": [
						0,
						0,
						0
					]
				},
				"c8": {
					"scale": [
						0,
						0,
						0
					]
				},
				"c9": {
					"scale": [
						0,
						0,
						0
					]
				},
				"c10": {
					"scale": [
						0,
						0,
						0
					]
				},
				"c11": {
					"scale": [
						0,
						0,
						0
					]
				},
				"c12": {
					"scale": [
						0,
						0,
						0
					]
				},
				"c13": {
					"scale": [
						0,
						0,
						0
					]
				},
				"c14": {
					"scale": [
						1,
						1,
						1
					]
				},
				"c15": {
					"scale": [
						0,
						0,
						0
					]
				}
			}
		},
		"animation.msdc0001.color15": {
			"loop": "hold_on_last_frame",
			"bones": {
				"c1": {
					"scale": [
						0,
						0,
						0
					]
				},
				"c2": {
					"scale": [
						0,
						0,
						0
					]
				},
				"c3": {
					"scale": [
						0,
						0,
						0
					]
				},
				"c4": {
					"scale": [
						0,
						0,
						0
					]
				},
				"c5": {
					"scale": [
						0,
						0,
						0
					]
				},
				"c6": {
					"scale": [
						0,
						0,
						0
					]
				},
				"c7": {
					"scale": [
						0,
						0,
						0
					]
				},
				"c8": {
					"scale": [
						0,
						0,
						0
					]
				},
				"c9": {
					"scale": [
						0,
						0,
						0
					]
				},
				"c10": {
					"scale": [
						0,
						0,
						0
					]
				},
				"c11": {
					"scale": [
						0,
						0,
						0
					]
				},
				"c12": {
					"scale": [
						0,
						0,
						0
					]
				},
				"c13": {
					"scale": [
						0,
						0,
						0
					]
				},
				"c14": {
					"scale": [
						0,
						0,
						0
					]
				},
				"c15": {
					"scale": [
						1,
						1,
						1
					]
				}
			}
		}
	}
}